slab_utils/__init__.py
slab_utils/pickle_util.py
slab_utils/quick_logger.py
slab_utils/spatial_ref_trans.py
slab_utils-0.0.4.dist-info/LICENSE
slab_utils-0.0.4.dist-info/METADATA
slab_utils-0.0.4.dist-info/WHEEL
slab_utils-0.0.4.dist-info/top_level.txt
slab_utils-0.0.4.dist-info/RECORD
