Metadata-Version: 2.1
Name: slab-utils
Version: 0.0.4
Summary: A package for slab
Home-page: https://github.com/46319943/SLab-Utils
Author: Piao Yang
Author-email: 495384481@qq.com
Classifier: Programming Language :: Python :: 3
Classifier: License :: OSI Approved :: MIT License
Classifier: Operating System :: OS Independent
Requires-Python: >=3.6
License-File: LICENSE
Requires-Dist: pathlib
